{
  "timestamp": "2025-06-24T23:15:38.762Z",
  "version": "1.0.0",
  "developmentProcess": {
    "methodology": "Agile/Scrum",
    "phases": [
      "Planning",
      "Development",
      "Testing",
      "Deployment"
    ],
    "tools": [
      "Git",
      "GitHub",
      "VS Code",
      "TypeScript"
    ],
    "standards": [
      "CMMI Level 3",
      "ISO 27001"
    ]
  },
  "codingStandards": {
    "language": "TypeScript",
    "framework": "React",
    "linting": "ESLint",
    "formatting": "Prettier",
    "testing": "Vitest + Playwright"
  },
  "workflow": {
    "versionControl": "Git Flow",
    "ciCd": "GitHub Actions",
    "deployment": "Supabase",
    "monitoring": "Built-in analytics"
  },
  "architectureDecisions": {
    "pattern": "Component-based architecture",
    "stateManagement": "Zustand + React Query",
    "styling": "Tailwind CSS + shadcn/ui",
    "database": "Supabase (PostgreSQL)"
  },
  "qualityAssurance": {
    "testing": "Unit, Integration, E2E",
    "codeReview": "Pull Request process",
    "documentation": "Automated generation",
    "monitoring": "Performance tracking"
  },
  "testingStrategy": {
    "unit": "Vitest + React Testing Library",
    "integration": "API testing",
    "e2e": "Playwright",
    "performance": "K6 load testing"
  }
}